<?xml version='1.0' encoding='utf-8'?>
<nrml xmlns:gml="http://www.opengis.net/gml"
	xmlns="http://openquake.org/xmlns/nrml/0.5">
<sourceModel name="Hazard Model" investigation_time="1">
	<sourceGroup name="group 1" rup_interdep="indep"
        src_interdep="indep"  tectonicRegion="Active Shallow Crust">
        <multiFaultSource id="4" name="multifaultsource_4">
				<multiPlanesRupture probs_occur="0.99998439 0.00001561">
					<magnitude>7.200000000000001</magnitude>
					<sectionIndexes indexes="2033,2034,2035,2071,2072"/>
					<rake>19.02772132248875</rake>
				</multiPlanesRupture>
				<multiPlanesRupture probs_occur="0.99999680 0.00000320">
					<magnitude>7.700000000000001</magnitude>
					<sectionIndexes indexes="2059,2060,2061,2062,2063,2064,2073,2074,2075,2093"/>
					<rake>-65.97247457152879</rake>
				</multiPlanesRupture>
				<multiPlanesRupture probs_occur="0.99999698 0.00000302">
					<magnitude>7.700000000000001</magnitude>
					<sectionIndexes indexes="2060,2061,2062,2063,2064,2073,2074,2075,2076,2093"/>
					<rake>-65.5519950880028</rake>
				</multiPlanesRupture>
				<multiPlanesRupture probs_occur="0.99999784 0.00000216">
					<magnitude>7.9</magnitude>
					<sectionIndexes indexes="2082,2083,2084,2085,2086,2087,2088,2089,2090"/>
					<rake>-33.64179099028702</rake>
				</multiPlanesRupture>
				<multiPlanesRupture probs_occur="0.99999598 0.00000402">
					<magnitude>7.5</magnitude>
					<sectionIndexes indexes="2309,2310,2380,2382,2386"/>
					<rake>-78.40866825429225</rake>
				</multiPlanesRupture>
				<multiPlanesRupture probs_occur="0.99999790 0.00000210">
					<magnitude>8.0</magnitude>
					<sectionIndexes indexes="2351,2352,2353,2354,2355,2356,2357,2437,2438,2439,2440,2441,2442,2443"/>
					<rake>-59.56906888965615</rake>
				</multiPlanesRupture>
				<multiPlanesRupture probs_occur="0.99999737 0.00000263">
					<magnitude>7.9</magnitude>
					<sectionIndexes indexes="2352,2353,2354,2355,2356,2357,2437,2438,2439,2440,2441,2442,2443"/>
					<rake>-61.35760881100826</rake>
				</multiPlanesRupture>
				<multiPlanesRupture probs_occur="0.99999786 0.00000214">
					<magnitude>8.0</magnitude>
					<sectionIndexes indexes="2349,2350,2351,2352,2353,2354,2355,2356,2357,2437,2438,2439,2440,2441,2442"/>
					<rake>-51.679711542718</rake>
				</multiPlanesRupture>
				<multiPlanesRupture probs_occur="0.99998727 0.00001273">
					<magnitude>7.300000000000001</magnitude>
					<sectionIndexes indexes="2380,2381,2382,2386,2387"/>
					<rake>-77.99217705206885</rake>
				</multiPlanesRupture>
				<multiPlanesRupture probs_occur="0.99999765 0.00000235">
					<magnitude>8.0</magnitude>
					<sectionIndexes indexes="2309,2380,2381,2382,2383,2386,2387,2388,2389,2390,2391,2392,2394,2395,2396"/>
					<rake>-41.36500229650369</rake>
				</multiPlanesRupture>
				<multiPlanesRupture probs_occur="0.99999716 0.00000284">
					<magnitude>7.9</magnitude>
					<sectionIndexes indexes="2432,2433,2434,2435,2436,2450,2451,2452,2453,2470,2471,2472,2473,2474"/>
					<rake>-17.98579324625718</rake>
				</multiPlanesRupture>
				<multiPlanesRupture probs_occur="0.99999412 0.00000588">
					<magnitude>7.9</magnitude>
					<sectionIndexes indexes="2433,2434,2435,2436,2450,2451,2452,2453,2468,2469,2470,2471,2472,2473,2474"/>
					<rake>-19.669019167668637</rake>
				</multiPlanesRupture>
				<multiPlanesRupture probs_occur="0.99999584 0.00000416">
					<magnitude>8.0</magnitude>
					<sectionIndexes indexes="2433,2434,2435,2436,2450,2451,2452,2453,2468,2469,2470,2471,2472,2473,2474"/>
					<rake>-19.669019167668637</rake>
				</multiPlanesRupture>
				<multiPlanesRupture probs_occur="0.99999191 0.00000809">
					<magnitude>7.5</magnitude>
					<sectionIndexes indexes="2620,2621,2622,2623,2624,2625,2626,2627,2628"/>
					<rake>-19.25759850197195</rake>
				</multiPlanesRupture>
				<multiPlanesRupture probs_occur="0.99999384 0.00000616">
					<magnitude>7.6000000000000005</magnitude>
					<sectionIndexes indexes="2619,2620,2621,2624,2625,2626,2627,2745,2746"/>
					<rake>-13.611532690119322</rake>
				</multiPlanesRupture>
				<multiPlanesRupture probs_occur="0.99999301 0.00000699">
					<magnitude>7.6000000000000005</magnitude>
					<sectionIndexes indexes="2619,2620,2621,2624,2625,2626,2627,2628,2745,2746"/>
					<rake>-20.580526801018</rake>
				</multiPlanesRupture>
				<multiPlanesRupture probs_occur="0.99999866 0.00000134">
					<magnitude>8.4</magnitude>
					<sectionIndexes indexes="640,641,642,643,749,750,751,755,756,757,758,759,760,761,762,763,764,782,783,784,785,786,787,788,789,790,791,792,793,798,799,800,801,802,803,804,805,806,807,808,809,810,811,812,841,842,843,844,845,846,847,848"/>
					<rake>-44.21944707389251</rake>
				</multiPlanesRupture>
				<multiPlanesRupture probs_occur="0.99999029 0.00000971">
					<magnitude>7.5</magnitude>
					<sectionIndexes indexes="1788,1789,1790,1796,1797,1798,1799,1802,1803"/>
					<rake>-0.4476431799213903</rake>
				</multiPlanesRupture>
				<multiPlanesRupture probs_occur="0.99998282 0.00001718">
					<magnitude>7.6000000000000005</magnitude>
					<sectionIndexes indexes="1788,1789,1790,1796,1797,1798,1799,1802,1803"/>
					<rake>-0.4476431799213903</rake>
				</multiPlanesRupture>
	    </multiFaultSource>
	</sourceGroup>
    </sourceModel>
</nrml>
